sectra/__init__.py
sectra/api.py
sectra/cache.py
sectra/cli.py
sectra/config.py
sectra-0.2.0.dist-info/licenses/LICENSE
sectra-0.2.0.dist-info/METADATA
sectra-0.2.0.dist-info/WHEEL
sectra-0.2.0.dist-info/entry_points.txt
sectra-0.2.0.dist-info/top_level.txt
sectra-0.2.0.dist-info/RECORD
