Metadata-Version: 2.4
Name: sectra
Version: 0.2.0
Summary: Shodan-style CLI for the SecurityTrails API
Author: Sectra Contributors
License: MIT
Project-URL: Homepage, https://github.com/random-robbie/sectra
Keywords: securitytrails,cli,osint
Classifier: Programming Language :: Python :: 3
Classifier: License :: OSI Approved :: MIT License
Classifier: Environment :: Console
Requires-Python: >=3.9
License-File: LICENSE
Requires-Dist: click>=8.1
Requires-Dist: requests>=2.31
Dynamic: license-file
